{
	"pattrstorage" : 	{
		"name" : "p-tutorial-1",
		"slots" : 		{
			"1" : 			{
				"id" : 1,
				"data" : 				{
					"mo.sliders::voices" : [ 4.0 ],
					"mo.sliders::polarity" : [ 0.0 ],
					"mo.sliders::mute" : [ 0.0 ],
					"mo.sliders::[1]::mute" : [ 0.0 ],
					"mo.sliders::[1]::polarity" : [ 0.0 ],
					"mo.sliders::[1]::slider" : [ 0.0 ],
					"mo.sliders::[2]::mute" : [ 0.0 ],
					"mo.sliders::[2]::polarity" : [ 0.0 ],
					"mo.sliders::[2]::slider" : [ 0.10239357665698 ],
					"mo.sliders::[3]::mute" : [ 0.0 ],
					"mo.sliders::[3]::polarity" : [ 0.0 ],
					"mo.sliders::[3]::slider" : [ 0.187759430315516 ],
					"mo.sliders::[4]::mute" : [ 0.0 ],
					"mo.sliders::[4]::polarity" : [ 0.0 ],
					"mo.sliders::[4]::slider" : [ 1.0 ],
					"mo.scale::voices" : [ 4.0 ],
					"mo.scale::min" : [ 0.0 ],
					"mo.scale::max" : [ 1.0 ],
					"mo.scale::curve" : [ 1.0 ],
					"mo.scale::mode" : [ 0.0 ],
					"mo.scale::[1]::min" : [ 110.0 ],
					"mo.scale::[1]::max" : [ 1760.0 ],
					"mo.scale::[1]::curve" : [ 1.0 ],
					"mo.scale::[1]::mute" : [ 0.0 ],
					"mo.scale::[2]::min" : [ 1.0 ],
					"mo.scale::[2]::max" : [ 10.0 ],
					"mo.scale::[2]::curve" : [ 1.0 ],
					"mo.scale::[2]::mute" : [ 0.0 ],
					"mo.scale::[3]::min" : [ 0.0 ],
					"mo.scale::[3]::max" : [ 8.0 ],
					"mo.scale::[3]::curve" : [ 1.0 ],
					"mo.scale::[3]::mute" : [ 0.0 ],
					"mo.scale::[4]::min" : [ 0.0 ],
					"mo.scale::[4]::max" : [ 1.0 ],
					"mo.scale::[4]::curve" : [ 1.0 ],
					"mo.scale::[4]::mute" : [ 0.0 ]
				}

			}

		}

	}

}
