{
	"pattrstorage" : 	{
		"name" : "p-wave",
		"slots" : 		{
			"1" : 			{
				"id" : 1,
				"data" : 				{
					"mo.midi::port" : [ "IAC Driver Bus 1" ],
					"mo.midi::mute[1]" : [ 0.0 ],
					"mo.midi::device" : [ 0.0 ],
					"mo.pads::voices" : [ 4.0 ],
					"mo.pads::mute" : [ 0.0 ],
					"mo.pads::[1]::mode" : [ 0.0 ],
					"mo.pads::[1]::pad" : [ 0.0 ],
					"mo.pads::[2]::mode" : [ 0.0 ],
					"mo.pads::[2]::pad" : [ 0.0 ],
					"mo.pads::[3]::mode" : [ 0.0 ],
					"mo.pads::[3]::pad" : [ 0.0 ],
					"mo.pads::[4]::mode" : [ 1.0 ],
					"mo.pads::[4]::pad" : [ 0.0 ],
					"mo.sliders::voices" : [ 4.0 ],
					"mo.sliders::polarity" : [ 0.0 ],
					"mo.sliders::mute" : [ 0.0 ],
					"mo.sliders::[1]::mute" : [ 0.0 ],
					"mo.sliders::[1]::slider" : [ 0.0 ],
					"mo.sliders::[1]::polarity" : [ 0.0 ],
					"mo.sliders::[2]::mute" : [ 0.0 ],
					"mo.sliders::[2]::slider" : [ 0.0 ],
					"mo.sliders::[2]::polarity" : [ 0.0 ],
					"mo.sliders::[3]::mute" : [ 0.0 ],
					"mo.sliders::[3]::slider" : [ 0.0 ],
					"mo.sliders::[3]::polarity" : [ 0.0 ],
					"mo.sliders::[4]::mute" : [ 0.0 ],
					"mo.sliders::[4]::slider" : [ 0.0 ],
					"mo.sliders::[4]::polarity" : [ 0.0 ],
					"mo.send::send" : [ "gyroscope-vibrato" ],
					"mo.send::mute" : [ 0.0 ],
					"mo.send[1]::send" : [ "buttons-tap" ],
					"mo.send[1]::mute" : [ 0.0 ]
				}

			}

		}

	}

}
